{
  "userid": "wonm",
  "guid": "664846a4-1100-4ade-a302-e6a4894ec845",
  "lastStatus": "deleted",
  "items": [
    {
      "seqNo": 0,
      "time": 1370999020,
      "scriptId": null,
      "historyId": "2520313017798432731b1c57aa0-80c3-4801-9540-4ba08aa0f051",
      "updateSize": 1792,
      "ast": {
        "textVersion": "v2.2,js,ctx",
        "jsonVersion": "v1.0,resolved,short",
        "name": "my popper",
        "comment": "",
        "autoIcon": "AdminUser",
        "autoColor": "#FF0038",
        "platform": "current",
        "rootId": "MBobDj4kWyeknjyMpciVcsWt",
        "showAd": false,
        "isLibrary": false,
        "allowExport": true,
        "hasUniqueIds": false,
        "decls": [
          {
            "name": "main",
            "inParameters": [],
            "outParameters": [],
            "isPrivate": false,
            "isOffloaded": false,
            "isTest": false,
            "isAsync": false,
            "nodeType": "action",
            "body": [
              {
                "expr": ":data #tUcmrMhXgkJkzvquV4dy9Kaq ,:= :media .create_landscape_board ,( ,8 ,0 ,0 ,, ,4 ,8 ,0 ,)",
                "nodeType": "exprStmt",
                "id": "Au7S4f77jsbZGn4QEhdl5jJi",
                "locals": []
              },
              {
                "expr": ":data #tUcmrMhXgkJkzvquV4dy9Kaq .post_to_wall",
                "nodeType": "exprStmt",
                "id": "XGrz3lGtsqMY2fBmw1iv81sz",
                "locals": []
              },
              {
                "expr": ":data #uYZXqBDeb9XQLJM9udcDtl3F ,:= :data #tUcmrMhXgkJkzvquV4dy9Kaq .create_sprite_set",
                "nodeType": "exprStmt",
                "id": "hgylt82u7b18eSX6eTdsiKBv",
                "locals": []
              },
              {
                "expr": "",
                "nodeType": "exprStmt",
                "id": "ZuzKdodznIdaJZvX0e2P8Okp",
                "locals": []
              }
            ],
            "id": "xMdpwn648PdQtuNDY0eHyLyb"
          },
          {
            "name": "board",
            "comment": "",
            "type": "Board",
            "isReadonly": false,
            "isTransient": true,
            "nodeType": "data",
            "id": "tUcmrMhXgkJkzvquV4dy9Kaq"
          },
          {
            "name": "gameloop",
            "inParameters": [],
            "outParameters": [],
            "isPrivate": true,
            "isOffloaded": false,
            "isTest": false,
            "isAsync": true,
            "nodeType": "event",
            "eventName": "gameloop",
            "eventVariableId": null,
            "body": [
              {
                "expr": ":data #tUcmrMhXgkJkzvquV4dy9Kaq .evolve",
                "nodeType": "exprStmt",
                "id": "x9zW5bml88XSSxtglA5V1TBs",
                "locals": []
              },
              {
                "expr": ":data #tUcmrMhXgkJkzvquV4dy9Kaq .update_on_wall",
                "nodeType": "exprStmt",
                "id": "OiQiJscqLwBucVqwQuP3oIF1",
                "locals": []
              }
            ],
            "id": "pDP2liLO1ZIfLzonUaNr4qEf"
          },
          {
            "name": "bubbles",
            "comment": "",
            "type": "Sprite Set",
            "isReadonly": false,
            "isTransient": true,
            "nodeType": "data",
            "id": "uYZXqBDeb9XQLJM9udcDtl3F"
          }
        ],
        "deletedDecls": [],
        "nodeType": "app",
        "id": "app"
      }
    },
    {
      "seqNo": 1,
      "time": 1370999041,
      "scriptId": null,
      "historyId": "2520313017580321691a4aa9647-b4bf-48ff-ae83-e0dadaba32f3",
      "updateSize": 45,
      "updates": {
        "app": {
          "rootId": "Dhf2IsGFReuXGQyVo6Znb4cW"
        }
      }
    },
    {
      "seqNo": 2,
      "time": 1370999054,
      "scriptId": null,
      "historyId": "2520313017456267131db13bedd-6d84-49f8-90e2-e224c1b80a0d",
      "updateSize": 152,
      "updates": {
        "ZuzKdodznIdaJZvX0e2P8Okp": {
          "expr": ":data #tUcmrMhXgkJkzvquV4dy9Kaq .create_ellipse ,( ,2 ,0 ,, ,2 ,0 ,)"
        },
        "app": {
          "rootId": "oUywCl2VpA3NlViT4IfyNWXD"
        }
      }
    },
    {
      "seqNo": 3,
      "time": 1370999081,
      "scriptId": null,
      "historyId": "25203130171881592916aafbd55-99f2-4623-8df1-2d7972db03c9",
      "updateSize": 279,
      "updates": {
        "ZuzKdodznIdaJZvX0e2P8OkpL0": {
          "name": "x",
          "type": "Unknown",
          "nodeType": "localDef"
        },
        "ZuzKdodznIdaJZvX0e2P8Okp": {
          "expr": ":data $ZuzKdodznIdaJZvX0e2P8OkpL0 ,:= .create_ellipse ,( ,2 ,0 ,, ,2 ,0 ,)",
          "locals": [
            "ZuzKdodznIdaJZvX0e2P8OkpL0"
          ]
        },
        "app": {
          "rootId": "glJEsBXHW9wXmd7iX2yaJfMz"
        }
      }
    },
    {
      "seqNo": 4,
      "time": 1370999094,
      "scriptId": null,
      "historyId": "25203130170598862517bbe0354-8037-4627-9881-7ee38ceb8808",
      "updateSize": 198,
      "updates": {
        "ZuzKdodznIdaJZvX0e2P8Okp": {
          "expr": ":data #tUcmrMhXgkJkzvquV4dy9Kaq .create_ellipse ,( ,2 ,0 ,, ,2 ,0 ,)",
          "locals": []
        },
        "app": {
          "rootId": "xkKsbMQobP7WhZmKfFOS2ebx"
        },
        "ZuzKdodznIdaJZvX0e2P8OkpL0": null
      }
    },
    {
      "seqNo": 5,
      "time": 1370999157,
      "scriptId": null,
      "historyId": "252031301642555185119e5f92e-439a-4462-a924-056b1e8d688a",
      "updateSize": 45,
      "updates": {
        "app": {
          "rootId": "XT6EDf4zWWSE6yrIzWgfnHjn"
        }
      }
    },
    {
      "seqNo": 6,
      "time": 1370999170,
      "scriptId": null,
      "historyId": "25203130162960800281cd98e94-aa29-4e6f-bc27-fb143852b09c",
      "updateSize": 45,
      "updates": {
        "app": {
          "rootId": "de8ip62NmDsqkNeqUdJHhmFu"
        }
      }
    },
    {
      "seqNo": 7,
      "time": 1371000492,
      "scriptId": null,
      "historyId": "2520313003075346494007f2776-5895-44a9-a42f-6dc689da1bd9",
      "updateSize": 45,
      "updates": {
        "app": {
          "rootId": "x45wnk4rXibuaDiZ2xal1RAn"
        }
      }
    }
  ]
}